MANIFEST.in
installer.command
installer.py
setup.py
music21/__init__.py
music21/articulations.py
music21/bar.py
music21/base.py
music21/beam.py
music21/chord.py
music21/chordTables.py
music21/clef.py
music21/common.py
music21/configure.py
music21/converter.py
music21/defaults.py
music21/derivation.py
music21/duration.py
music21/dynamics.py
music21/editorial.py
music21/environment.py
music21/expressions.py
music21/graph.py
music21/instrument.py
music21/interval.py
music21/intervalNetwork.py
music21/key.py
music21/layout.py
music21/license.txt
music21/medren.py
music21/metadata.py
music21/meter.py
music21/node.py
music21/note.py
music21/pitch.py
music21/ratios.py
music21/repeat.py
music21/roman.py
music21/scale.py
music21/search.py
music21/serial.py
music21/sieve.py
music21/spanner.py
music21/stream.py
music21/tempo.py
music21/text.py
music21/tie.py
music21/tinyNotation.py
music21/voiceLeading.py
music21/xmlnode.py
music21.egg-info/PKG-INFO
music21.egg-info/SOURCES.txt
music21.egg-info/dependency_links.txt
music21.egg-info/top_level.txt
music21/abc/__init__.py
music21/abc/base.py
music21/abc/testFiles.py
music21/abc/translate.py
music21/abj/__init__.py
music21/abj/translate.py
music21/analysis/__init__.py
music21/analysis/correlate.py
music21/analysis/discrete.py
music21/analysis/metrical.py
music21/analysis/patel.py
music21/analysis/search.py
music21/analysis/windowed.py
music21/composition/__init__.py
music21/composition/aug30.py
music21/composition/phasing.py
music21/corpus/__init__.py
music21/corpus/base.py
music21/corpus/license.txt
music21/corpus/virtual.py
music21/corpus/airdsAirs/__init__.py
music21/corpus/airdsAirs/book1.abc
music21/corpus/airdsAirs/book2.abc
music21/corpus/airdsAirs/book3.abc
music21/corpus/airdsAirs/book4.abc
music21/corpus/airdsAirs/book5.abc
music21/corpus/airdsAirs/book6.abc
music21/corpus/bach/__init__.py
music21/corpus/bach/bwv1.6.xml
music21/corpus/bach/bwv10.7.xml
music21/corpus/bach/bwv101.7.xml
music21/corpus/bach/bwv102.7.xml
music21/corpus/bach/bwv103.6.xml
music21/corpus/bach/bwv104.6.xml
music21/corpus/bach/bwv108.6.xml
