Metadata-Version: 1.0
Name: music21
Version: 0.3.6.a10
Summary: A Toolkit for Computer-Aided Musical Analysis and Manipulation.
Home-page: http://code.google.com/p/music21
Author: Michael Scott Cuthbert, Christopher Ariza, others
Author-email: UNKNOWN
License: LGPL
Download-URL: http://music21.googlecode.com/files/music21-0.3.6.a10.tar.gz
Platform: UNKNOWN
Classifier: Development Status :: 3 - Alpha
Classifier: Environment :: Console
Classifier: Intended Audience :: End Users/Desktop
Classifier: Intended Audience :: Developers
Classifier: Intended Audience :: Education
Classifier: Intended Audience :: Science/Research
Classifier: License :: OSI Approved :: GNU Library or Lesser General Public License (LGPL)
Classifier: Natural Language :: English
Classifier: Operating System :: MacOS
Classifier: Operating System :: Microsoft :: Windows
Classifier: Operating System :: POSIX
Classifier: Operating System :: OS Independent
Classifier: Programming Language :: Python
Classifier: Topic :: Multimedia :: Sound/Audio
Classifier: Topic :: Artistic Software
